meinelib/__init__.py
meinelib/debug.py
meinelib-0.1.1.dist-info/licenses/LICENSE
meinelib-0.1.1.dist-info/METADATA
meinelib-0.1.1.dist-info/WHEEL
meinelib-0.1.1.dist-info/top_level.txt
meinelib-0.1.1.dist-info/RECORD
